unpy/__init__.py
unpy/__main__.py
unpy/_cst.py
unpy/_meta.py
unpy/_stdlib.py
unpy/_types.py
unpy/exceptions.py
unpy/main.py
unpy/py.typed
unpy/transformers.py
unpy/visitors.py
unpy-0.3.0.dist-info/METADATA
unpy-0.3.0.dist-info/WHEEL
unpy-0.3.0.dist-info/entry_points.txt
unpy-0.3.0.dist-info/licenses/LICENSE
unpy-0.3.0.dist-info/RECORD
