Metadata-Version: 2.3
Name: unpy
Version: 0.3.0
Summary: Backports Python Typing Stubs
Project-URL: Repository, https://github.com/jorenham/unpy
Project-URL: Documentation, https://github.com/jorenham/unpy?tab=readme-ov-file#unpy
Project-URL: Issues, https://github.com/jorenham/unpy/issues
Project-URL: Changelog, https://github.com/jorenham/unpy/releases
Project-URL: Funding, https://github.com/sponsors/jorenham
Author-email: Joren Hammudoglu <jhammudoglu@gmail.com>
License-Expression: BSD-3-Clause
License-File: LICENSE
Classifier: Development Status :: 3 - Alpha
Classifier: Intended Audience :: Developers
Classifier: License :: OSI Approved :: BSD License
Classifier: Natural Language :: English
Classifier: Operating System :: OS Independent
Classifier: Programming Language :: Python :: 3
Classifier: Programming Language :: Python :: 3.12
Classifier: Programming Language :: Python :: 3.13
Classifier: Topic :: Software Development :: Code Generators
Classifier: Topic :: Software Development :: Compilers
Classifier: Typing :: Typed
Requires-Python: >=3.12
Requires-Dist: libcst<2,>=1.4.0
Requires-Dist: typer-slim<1,>=0.12.5
